Metadata-Version: 2.4
Name: mathspractice
Version: 0.0.17
Summary: Basic Mathematics Practice
Author-email: David Johnston <c0d3@gpobox.net>
License-Expression: MIT
Classifier: Programming Language :: Python :: 3
Classifier: Operating System :: OS Independent
Classifier: Development Status :: 4 - Beta
Classifier: Natural Language :: English
Classifier: Operating System :: POSIX :: Linux
Classifier: Topic :: Utilities
Requires-Python: >=3.10
License-File: LICENSE.md
Requires-Dist: flask<3.2,>=3.1
Provides-Extra: dev
Requires-Dist: wheel; extra == "dev"
Requires-Dist: build; extra == "dev"
Requires-Dist: twine; extra == "dev"
Provides-Extra: test
Requires-Dist: pytest; extra == "test"
Requires-Dist: coverage; extra == "test"
Requires-Dist: pytest-cov; extra == "test"
Dynamic: license-file
